variant_tools/__init__.py
variant_tools/_assoTests.cpython-38-darwin.so
variant_tools/_cgatools.cpython-38-darwin.so
variant_tools/_ucsctools.cpython-38-darwin.so
variant_tools/_version.py
variant_tools/_vt_sqlite3.cpython-38-darwin.so
variant_tools/_vt_sqlite3_ext.cpython-38-darwin.so
variant_tools/accessor.py
variant_tools/annotation.py
variant_tools/assoTests.py
variant_tools/association.py
variant_tools/association_hdf5.py
variant_tools/cgatools.py
variant_tools/checking_asso_result.py
variant_tools/compare.py
variant_tools/cplinkio.cpython-38-darwin.so
variant_tools/exporter.py
variant_tools/exporter_reader.py
variant_tools/geno_store.py
variant_tools/importer.py
variant_tools/importer_allele_hdf5.py
variant_tools/io_vcf_read.cpython-38-darwin.so
variant_tools/liftOver.py
variant_tools/merge_sort_parallel.py
variant_tools/meta.py
variant_tools/phenotype.py
variant_tools/pipeline.py
variant_tools/plinkfile.py
variant_tools/plot.py
variant_tools/preprocessor.py
variant_tools/project.py
variant_tools/rtester.py
variant_tools/simulation.py
variant_tools/site_options.py
variant_tools/tester.py
variant_tools/text_reader.py
variant_tools/ucsctools.py
variant_tools/update.py
variant_tools/utils.py
variant_tools/variant.py
variant_tools/vt_sqlite3.py
variant_tools/vtools.py
variant_tools/vtools_report.py
variant_tools/worker_zmq.py
variant_tools-3.1.3.dist-info/LICENSE
variant_tools-3.1.3.dist-info/METADATA
variant_tools-3.1.3.dist-info/WHEEL
variant_tools-3.1.3.dist-info/entry_points.txt
variant_tools-3.1.3.dist-info/top_level.txt
variant_tools-3.1.3.dist-info/RECORD
