Metadata-Version: 2.1
Name: variant-tools
Version: 3.1.3
Summary: Variant tools: an integrated annotation and analysis package for next-generation sequencing data
Home-page: http://varianttools.sourceforge.net
Author: Bo Peng
Author-email: bpeng@mdanderson.org
Maintainer: Bo Peng
Maintainer-email: varianttools-devel@lists.sourceforge.net
License: GPL3
Platform: UNKNOWN
Classifier: Development Status :: 5 - Production/Stable
Classifier: Environment :: Console
Classifier: Intended Audience :: Education
Classifier: Intended Audience :: Science/Research
Classifier: License :: OSI Approved :: GNU General Public License (GPL)
Classifier: Natural Language :: English
Classifier: Operating System :: POSIX :: Linux
Classifier: Operating System :: MacOS :: MacOS X
Classifier: Programming Language :: C++
Classifier: Programming Language :: Python
Classifier: Programming Language :: Python :: 3
Classifier: Topic :: Scientific/Engineering :: Bio-Informatics
Requires-Dist: pyzmq
Requires-Dist: tables
Requires-Dist: numpy
Requires-Dist: Cython
Requires-Dist: scipy
Requires-Dist: pycurl
